trame/__init__.py
trame/modules/__init__.py
trame/modules/xterm.py
trame/widgets/__init__.py
trame/widgets/xterm.py
trame_xterm/__init__.py
trame_xterm/module/__init__.py
trame_xterm/module/serve/style.css
trame_xterm/module/serve/trame-xterm.mjs
trame_xterm/module/serve/trame-xterm.umd.js
trame_xterm/utils/__init__.py
trame_xterm/utils/terminal.py
trame_xterm/widgets/__init__.py
trame_xterm/widgets/xterm.py
trame_xterm-0.2.1.dist-info/LICENSE
trame_xterm-0.2.1.dist-info/METADATA
trame_xterm-0.2.1.dist-info/WHEEL
trame_xterm-0.2.1.dist-info/top_level.txt
trame_xterm-0.2.1.dist-info/RECORD
